dipa/__init__.py
dipa-0.1.dist-info/METADATA
dipa-0.1.dist-info/RECORD
dipa-0.1.dist-info/WHEEL
dipa-0.1.dist-info/top_level.txt
