Metadata-Version: 2.1
Name: dipa
Version: 0.1
Summary: The funniest joke in the world
Home-page: UNKNOWN
Author: Flying Circus
Author-email: amiragibraihan@gmail.com
License: MIT
Platform: UNKNOWN
